{
  "Sữa rửa mặt kiểm soát dầu CeraVe": "img/srmCerave.jpg",
  "Toner cân bằng dầu Paula's Choice": "img/tonerPaulachoise.jpg",
  "Kem dưỡng ẩm không dầu Neutrogena": "img/kemduongNeutrogena.jpg",
  "Serum Niacinamide 10% The Ordinary": "img/serum_10%nia_ordinary.jpg",
  "Kem dưỡng ẩm sâu Cetaphil": "img/kemduongCetaphil.jpg",
  "Serum Hyaluronic Acid Vichy": "img/serum_HA_Vichy.jpg",
  "Sữa rửa mặt dịu nhẹ Bioderma": "img/srmBioderma.jpg",
  "Dầu dưỡng mặt Kiehl's Midnight Recovery": "img/dauduongMidnightRevery.jpg",
  "Kem dưỡng cân bằng ẩm La Roche-Posay": "img/kemduongLaRoche_Posay.jpg",
  "Toner hoa hồng Klairs": "img/tonerKlairs.jpg",
  "Serum Vitamin C Skinceuticals": "img/serumC_Skinceuticals.jpg",
  "Kem dưỡng phục hồi Avène Cicalfate": "img/kemduongAvencecicalfate.jpg",
  "Kem chống nắng SPF50+ Anessa": "img/kcnAnessa.jpg",
  "Xịt khoáng Evian": "img/xitkhoang_Evian.jpg",
  "Sữa rửa mặt Gentle Skin Cleanser Eucerin": "img/srm_Eucerin.jpg",
  "Sữa rửa mặt Simple": "img/srmSimple.jpg",
  "Sữa rửa mặt Cetaphil": "img/srmCentaphil.jpg",
  "Serum vitamin C Klairs": "img/serum_CKlaris.jpg",
  "Nước tẩy trang Bioderma Sensibio H2O": "img/taytrang_Bioderma.jpg",
  "Tẩy tế bào chết Paula's Choice 2% BHA": "img/taytbc_Paulachoice.jpg",
  "Mặt nạ đất sét Kiehl's Rare Earth": "img/matna_Kiehl'sRare Earth.jpg",
  "Kem chống nắng La Roche-Posay Anthelios": "img/kcn_LarochePosay.jpg",
  "Kem dưỡng mắt Estee Lauder ANR": "img/duongmat_EsteeLauderANR.jpg",
  "Nước tẩy trang L'Oreal Micellar Water": "img/taytrang_LOreal.jpg",
  "Nước tẩy trang Garnier Micellar": "img/taytrang_Garnier.jpg",
  "Sữa rửa mặt Cosrx Low pH Good Morning": "img/srm_Goodmorning.jpg",
  "Sữa rửa mặt Senka Perfect Whip": "img/srmSenka.jpg",
  "Sữa rửa mặt Hada Labo Advanced Nourish": "img/srm_hadalabo.jpg",
  "Toner làm dịu da Anua Heartleaf 77%": "img/toner_77%.jpg",
  "Toner cấp ẩm Hada Labo Gokujyun": "img/toner_hadalabo.jpg"
}
